doretta/__init__.py
doretta/dot_validator.py
doretta/frontend.py
doretta-1.0.1.dist-info/LICENSE
doretta-1.0.1.dist-info/METADATA
doretta-1.0.1.dist-info/WHEEL
doretta-1.0.1.dist-info/entry_points.txt
doretta-1.0.1.dist-info/top_level.txt
doretta-1.0.1.dist-info/RECORD
